hasta/__init__.py
hasta/hasta.py
hasta/http/__init__.py
hasta/http/app.py
hasta/http/environ.py
hasta/http/init.py
hasta/http/main.py
hasta/http/request.py
hasta/http/response.py
Hasta-0.0.0a2.post1.dist-info/LICENSE.md
Hasta-0.0.0a2.post1.dist-info/METADATA
Hasta-0.0.0a2.post1.dist-info/WHEEL
Hasta-0.0.0a2.post1.dist-info/top_level.txt
Hasta-0.0.0a2.post1.dist-info/RECORD
