Metadata-Version: 2.1
Name: Hasta
Version: 0.0.0a2.post1
Summary: A simple WSGI Server, implemented in CPython 3.9.9 .
Home-page: UNKNOWN
Author: Anoki Youssou
Author-email: anoki.youssou@gmail.com
License: UNKNOWN
Platform: UNKNOWN
Classifier: Programming Language :: Python :: 3 :: Only
Classifier: Operating System :: OS Independent
Classifier: Topic :: Internet :: WWW/HTTP :: WSGI
Classifier: Natural Language :: English
Classifier: Development Status :: 3 - Alpha
Classifier: License :: OSI Approved :: MIT License
Requires-Python: >=3.9.9
License-File: LICENSE.md
